axis_batch/__init__.py
axis_batch/_main.py
axis_batch/py.typed
axis_batch-0.1.1.dist-info/licenses/LICENSE
axis_batch-0.1.1.dist-info/METADATA
axis_batch-0.1.1.dist-info/WHEEL
axis_batch-0.1.1.dist-info/top_level.txt
axis_batch-0.1.1.dist-info/RECORD
